auto_red_test/__init__.py
auto_red_test/dict_format_print.py
auto_red_test/dict_replace.py
auto_red_test/faker_config.py
auto_red_test/generate_test_case.py
auto_red_test/thrift_fake.py
auto_red_test-0.2.1.dist-info/LICENSE
auto_red_test-0.2.1.dist-info/METADATA
auto_red_test-0.2.1.dist-info/WHEEL
auto_red_test-0.2.1.dist-info/__init__.py
auto_red_test-0.2.1.dist-info/top_level.txt
auto_red_test-0.2.1.dist-info/RECORD
