Metadata-Version: 2.1
Name: auto-red-test
Version: 0.2.1
Summary: Auto Create PyTest Frame and Fake Test Parameters For Red
Home-page: https://github.com/qjjayy/red_test
Author: Junjie Qiu
Author-email: xiaohaixie@qq.com
License: MIT
Keywords: auto red test
Platform: any
Classifier: Intended Audience :: Developers
Classifier: License :: OSI Approved :: MIT License
Classifier: Programming Language :: Python :: 2.7
Requires-Dist: pytest
Requires-Dist: pyaml
Requires-Dist: Faker
Requires-Dist: bson
Requires-Dist: dictdiffer
